<annotation>
	<folder>ImFuente</folder>
	<filename>01 (161).jpg</filename>
	<path>C:\Users\Txusel\Desktop\ProyectoEstancia\ImFuente\01 (161).jpg</path>
	<source>
		<database>Unknown</database>
	</source>
	<size>
		<width>868</width>
		<height>1160</height>
		<depth>3</depth>
	</size>
	<segmented>0</segmented>
	<object>
		<name>Auto</name>
		<pose>Unspecified</pose>
		<truncated>0</truncated>
		<difficult>0</difficult>
		<bndbox>
			<xmin>162</xmin>
			<ymin>204</ymin>
			<xmax>604</xmax>
			<ymax>418</ymax>
		</bndbox>
	</object>
	<object>
		<name>Auto</name>
		<pose>Unspecified</pose>
		<truncated>0</truncated>
		<difficult>0</difficult>
		<bndbox>
			<xmin>587</xmin>
			<ymin>208</ymin>
			<xmax>722</xmax>
			<ymax>303</ymax>
		</bndbox>
	</object>
</annotation>
